fluentcms_contactform/__init__.py
fluentcms_contactform/admin.py
fluentcms_contactform/appsettings.py
fluentcms_contactform/content_plugins.py
fluentcms_contactform/email.py
fluentcms_contactform/models.py
fluentcms_contactform/utils.py
fluentcms_contactform/forms/__init__.py
fluentcms_contactform/forms/base.py
fluentcms_contactform/forms/captcha.py
fluentcms_contactform/forms/compact.py
fluentcms_contactform/forms/default.py
fluentcms_contactform/forms/recaptcha.py
fluentcms_contactform/locale/en/LC_MESSAGES/django.mo
fluentcms_contactform/locale/en/LC_MESSAGES/django.po
fluentcms_contactform/locale/nl/LC_MESSAGES/django.mo
fluentcms_contactform/locale/nl/LC_MESSAGES/django.po
fluentcms_contactform/migrations/0001_initial.py
fluentcms_contactform/migrations/__init__.py
fluentcms_contactform/templates/fluentcms_contactform/forms/base.html
fluentcms_contactform/templates/fluentcms_contactform/forms/default.html
fluentcms_contactform/templates/fluentcms_contactform/staff_email/default.txt
fluentcms_contactform/tests/__init__.py
fluentcms_contactform/tests/test_all.py
fluentcms_contactform/tests/urls.py
fluentcms_contactform-3.0.dist-info/AUTHORS
fluentcms_contactform-3.0.dist-info/LICENSE
fluentcms_contactform-3.0.dist-info/METADATA
fluentcms_contactform-3.0.dist-info/WHEEL
fluentcms_contactform-3.0.dist-info/top_level.txt
fluentcms_contactform-3.0.dist-info/RECORD
