Metadata-Version: 2.1
Name: fluentcms-contactform
Version: 3.0
Summary: A contact form plugin django-fluent-contents
Home-page: https://github.com/edoburu/fluentcms-contactform
Author: Diederik van der Boor
Author-email: opensource@edoburu.nl
License: Apache 2.0
Download-URL: https://github.com/edoburu/fluentcms-contactform/zipball/master
Platform: UNKNOWN
Classifier: Development Status :: 5 - Production/Stable
Classifier: Environment :: Web Environment
Classifier: Framework :: Django
Classifier: Intended Audience :: Developers
Classifier: License :: OSI Approved :: Apache Software License
Classifier: Operating System :: OS Independent
Classifier: Programming Language :: Python
Classifier: Programming Language :: Python :: 3
Classifier: Programming Language :: Python :: 3.6
Classifier: Programming Language :: Python :: 3.7
Classifier: Programming Language :: Python :: 3.8
Classifier: Programming Language :: Python :: 3.9
Classifier: Framework :: Django
Classifier: Framework :: Django :: 2.2
Classifier: Framework :: Django :: 3.1
Classifier: Framework :: Django :: 3.2
Classifier: Framework :: Django :: 4.0
Classifier: Topic :: Internet :: WWW/HTTP
Classifier: Topic :: Internet :: WWW/HTTP :: Dynamic Content
Classifier: Topic :: Software Development :: Libraries :: Python Modules
Requires: Django (>=1.10)
Requires-Dist: django-fluent-contents (>=2.0)
Requires-Dist: django-phonenumber-field (>=0.7.2)
Requires-Dist: django-crispy-forms (>=1.3)
Provides-Extra: captcha
Requires-Dist: django-simple-captcha (>=0.5.6) ; extra == 'captcha'
Provides-Extra: recaptcha
Requires-Dist: django-recaptcha (>=1.3.0) ; extra == 'recaptcha'
